{"id":"sqlalchemy.dialects.mssql.aioodbc","path":"/opt/homebrew/Caskroom/miniforge/base/envs/tree_machine/lib/python3.11/site-packages/sqlalchemy/dialects/mssql/aioodbc.py","mtime":1720740478,"size":2022,"hash":"51077d79c48c20c2fbd774c39cb02f8ae0552657bb3fb8b516da8665978f9366","data_mtime":1719445043,"dependencies":["sqlalchemy.dialects.mssql.pyodbc","sqlalchemy.connectors.aioodbc","__future__","builtins","abc","sqlalchemy.connectors","sqlalchemy.connectors.pyodbc","sqlalchemy.dialects.mssql.base","sqlalchemy.engine","sqlalchemy.engine.default","sqlalchemy.engine.interfaces","sqlalchemy.event","sqlalchemy.event.registry","typing"],"suppressed":[],"options":{"disable_error_code":[],"extra_checks":false,"ignore_missing_imports":true,"implicit_optional":false,"implicit_reexport":true,"disallow_any_decorated":false,"plugins":[],"strict_equality":false,"bazel":false,"disallow_any_unimported":false,"strict_concatenate":false,"always_true":[],"follow_imports_for_stubs":false,"new_type_inference":false,"follow_imports":"normal","disallow_untyped_calls":false,"enabled_error_codes":[],"local_partial_types":false,"disallow_incomplete_defs":false,"warn_unreachable":false,"disable_memoryview_promotion":false,"disabled_error_codes":[],"disallow_any_expr":false,"allow_redefinition":false,"allow_untyped_globals":false,"disable_bytearray_promotion":false,"disallow_subclassing_any":false,"enable_error_code":[],"check_untyped_defs":false,"disallow_any_explicit":false,"mypyc":false,"ignore_errors":false,"always_false":[],"disallow_any_generics":false,"warn_return_any":false,"disallow_untyped_decorators":false,"platform":"darwin","disallow_untyped_defs":false,"warn_no_return":true,"strict_optional":true,"warn_unused_ignores":false},"dep_prios":[5,5,5,5,30,30,30,30,30,30,30,30,30,30],"dep_lines":[46,48,44,1,1,1,1,1,1,1,1,1,1,1],"interface_hash":"908e2bbb425a6f5860b6dce26114472002f317c3f22bd3514eb642f790693089","version_id":"1.6.0","ignore_all":true,"plugin_data":null}